cloudjet/core.py
cloudjet/init.py
cloudjet-0.1.0.dist-info/METADATA
cloudjet-0.1.0.dist-info/WHEEL
cloudjet-0.1.0.dist-info/top_level.txt
cloudjet-0.1.0.dist-info/RECORD
