Metadata-Version: 2.4
Name: cloudjet
Version: 0.1.0
Summary: A simple Python SDK for CloudJet Proxy Detection API
Author-email: Shehab Elden Ashraf <shehab.ashraf@cloudjet.org>
License: MIT
Project-URL: Homepage, https://cloudjet.org/
Requires-Python: >=3.7
Requires-Dist: requests
